{
  "title": "Near to Vima Beach Resorts",
  "timestamp": 1783253731,
  "media": [
    
  ],
  "label_values": [
    {
      "label": "Region",
      "value": "Asia Pacific"
    },
    {
      "label": "Marketing offer seen time",
      "timestamp_value": 0
    },
    {
      "label": "Update time",
      "timestamp_value": 1783253731
    },
    {
      "label": "Name",
      "value": "Cozzy Collection"
    },
    {
      "label": "First name",
      "value": ""
    },
    {
      "label": "Last name",
      "value": ""
    },
    {
      "dict": [
        {
          "dict": [
            {
              "label": "Email",
              "value": "analynpasumala23@gmail.com"
            },
            {
              "label": "Primary email",
              "value": "True"
            },
            {
              "label": "Update time",
              "timestamp_value": 1783253734
            },
            {
              "label": "Verified",
              "value": "False"
            },
            {
              "label": "Verification time",
              "timestamp_value": 0
            },
            {
              "label": "Update time",
              "timestamp_value": 1783253734
            },
            {
              "timestamp_value": 1783253733
            }
          ],
          "title": ""
        }
      ],
      "title": "Emails"
    },
    {
      "dict": [
        {
          "dict": [
            {
              "label": "Name",
              "value": "Analyn Pasumala"
            },
            {
              "label": "Street",
              "value": "Sabana-B Kinawahan,San Remigio,Cebu Philippines"
            },
            {
              "label": "Apt/suite/other",
              "value": "Sabana  B Kinawahan,San Remigio,Cebu Philippines"
            },
            {
              "label": "City",
              "value": "San Remigio"
            },
            {
              "label": "State",
              "value": "Central Visayas"
            },
            {
              "label": "Country",
              "value": "PH"
            },
            {
              "label": "ZIP/postal code",
              "value": "6011"
            },
            {
              "label": "First name",
              "value": "Analyn"
            },
            {
              "label": "Last name",
              "value": "Pasumala"
            },
            {
              "label": "Company",
              "value": ""
            },
            {
              "label": "Default address",
              "value": "True"
            },
            {
              "label": "Phone number"
            },
            {
              "label": "Zip code extension",
              "value": ""
            },
            {
              "label": "Update time",
              "timestamp_value": 1783253729
            },
            {
              "label": "Verified",
              "value": "True"
            },
            {
              "label": "Verification status"
            },
            {
              "label": "District",
              "value": ""
            },
            {
              "label": "Sub district",
              "value": ""
            },
            {
              "label": "Update time",
              "timestamp_value": 1783253729
            },
            {
              "timestamp_value": 1783253729
            }
          ],
          "title": ""
        },
        {
          "dict": [
            {
              "label": "Name",
              "value": "Analyn Pasumala"
            },
            {
              "label": "Street",
              "value": "Sabana-b Kinawahan,san Remigio,cebu Philippines"
            },
            {
              "label": "Apt/suite/other",
              "value": "Tabuelan - San Remigio Road"
            },
            {
              "label": "City",
              "value": "San Remigio"
            },
            {
              "label": "State",
              "value": "Central Visayas"
            },
            {
              "label": "Country",
              "value": "PH"
            },
            {
              "label": "ZIP/postal code",
              "value": "6011"
            },
            {
              "label": "First name",
              "value": "Analyn"
            },
            {
              "label": "Last name",
              "value": "Pasumala"
            },
            {
              "label": "Company",
              "value": ""
            },
            {
              "label": "Default address",
              "value": "False"
            },
            {
              "label": "Phone number"
            },
            {
              "label": "Zip code extension",
              "value": ""
            },
            {
              "label": "Update time",
              "timestamp_value": 1783253729
            },
            {
              "label": "Verified",
              "value": "True"
            },
            {
              "label": "Verification status"
            },
            {
              "label": "District",
              "value": ""
            },
            {
              "label": "Sub district",
              "value": ""
            },
            {
              "label": "Update time",
              "timestamp_value": 1783253729
            },
            {
              "timestamp_value": 1783253729
            },
            {
              "value": ""
            }
          ],
          "title": ""
        },
        {
          "dict": [
            {
              "label": "Name",
              "value": "Analyn Pasumala"
            },
            {
              "label": "Street",
              "value": "Sabana-b Kinawahan,san Remigio,cebu Philippines"
            },
            {
              "label": "Apt/suite/other",
              "value": ""
            },
            {
              "label": "City",
              "value": ""
            },
            {
              "label": "State",
              "value": "63_8"
            },
            {
              "label": "Country",
              "value": "PH"
            },
            {
              "label": "ZIP/postal code",
              "value": ""
            },
            {
              "label": "First name",
              "value": "Analyn"
            },
            {
              "label": "Last name",
              "value": "Pasumala"
            },
            {
              "label": "Company",
              "value": ""
            },
            {
              "label": "Default address",
              "value": "False"
            },
            {
              "label": "Phone number"
            },
            {
              "label": "Zip code extension",
              "value": ""
            },
            {
              "label": "Update time",
              "timestamp_value": 1783253729
            },
            {
              "label": "Verified",
              "value": "False"
            },
            {
              "label": "Verification status"
            },
            {
              "label": "District",
              "value": ""
            },
            {
              "label": "Sub district",
              "value": ""
            },
            {
              "label": "Update time",
              "timestamp_value": 1783253729
            },
            {
              "timestamp_value": 1783253729
            },
            {
              "value": ""
            }
          ],
          "title": ""
        }
      ],
      "title": "Mailing addresses"
    },
    {
      "dict": [
        
      ],
      "title": "Names used for automatically filling forms"
    },
    {
      "dict": [
        {
          "dict": [
            {
              "label": "Phone number",
              "value": "9365405908"
            },
            {
              "label": "Country code",
              "value": "PH"
            },
            {
              "label": "Verification status"
            },
            {
              "label": "Update time",
              "timestamp_value": 1783253734
            },
            {
              "label": "Update time",
              "timestamp_value": 1783253734
            },
            {
              "timestamp_value": 1783253733
            }
          ],
          "title": ""
        }
      ],
      "title": "Phones"
    }
  ],
  "fbid": "1348325570590498"
}